rtl/fault_detection.v
module fault_detection (
    input  wire       clk,
    input  wire       rst,
    input  wire       ch1,
    input  wire       ch2,
    input  wire       ch3,
    input  wire       ch4,

    output reg        fault,
    output reg [3:0]  fault_code
);

always @(posedge clk) begin
    if (rst) begin
        fault      <= 1'b0;
        fault_code <= 4'b0000;
    end
    else begin
        if (ch1) begin
            fault      <= 1'b1;
            fault_code <= 4'b1000;
        end
        else if (ch2) begin
            fault      <= 1'b1;
            fault_code <= 4'b0100;
        end
        else if (ch3) begin
            fault      <= 1'b1;
            fault_code <= 4'b0010;
        end
        else if (ch4) begin
            fault      <= 1'b1;
            fault_code <= 4'b0001;
        end
        else begin
            fault      <= 1'b0;
            fault_code <= 4'b0000;
        end
    end
end

endmodule

tb/fault_detection_tb.v
`timescale 1ns/1ps

module fault_detection_tb;

    reg clk;
    reg rst;
    reg ch1, ch2, ch3, ch4;

    wire fault;
    wire [3:0] fault_code;

    fault_detection dut (
        .clk(clk),
        .rst(rst),
        .ch1(ch1),
        .ch2(ch2),
        .ch3(ch3),
        .ch4(ch4),
        .fault(fault),
        .fault_code(fault_code)
    );

    always #5 clk = ~clk;

    initial begin
         $dumpfile("../simulation/waveform.vcd");
         $dumpvars(0, fault_detection_tb);

        clk = 0;
        rst = 1;
        ch1 = 0;
        ch2 = 0;
        ch3 = 0;
        ch4 = 0;

        #10;
        rst = 0;

        // Test 1: No fault
        #10;
        if (fault == 0 && fault_code == 4'b0000)
            $display("TEST 1 PASS: No fault");
        else
            $display("TEST 1 FAIL");

        // Test 2: CH1 fault
        ch1 = 1;
        #10;
        if (fault == 1 && fault_code == 4'b1000)
            $display("TEST 2 PASS: CH1 fault");
        else
            $display("TEST 2 FAIL");

        ch1 = 0;

        // Test 3: CH2 fault
        ch2 = 1;
        #10;
        if (fault == 1 && fault_code == 4'b0100)
            $display("TEST 3 PASS: CH2 fault");
        else
            $display("TEST 3 FAIL");

        ch2 = 0;

        // Test 4: CH3 fault
        ch3 = 1;
        #10;
        if (fault == 1 && fault_code == 4'b0010)
            $display("TEST 4 PASS: CH3 fault");
        else
            $display("TEST 4 FAIL");

        ch3 = 0;

        // Test 5: CH4 fault
        ch4 = 1;
        #10;
        if (fault == 1 && fault_code == 4'b0001)
            $display("TEST 5 PASS: CH4 fault");
        else
            $display("TEST 5 FAIL");

        ch4 = 0;

        // Test 6: Multiple faults
        ch1 = 1;
        ch3 = 1;
        #10;
        if (fault == 1 && fault_code == 4'b1000)
            $display("TEST 6 PASS: CH1 priority");
        else
            $display("TEST 6 FAIL");

        #10;
        $finish;

    end

endmodule

simulation/waveform.vcd
$date
	Tue Oct  6 22:05:58 2026
$end
$version
	Icarus Verilog
$end
$timescale
	1ps
$end
$scope module fault_detection_tb $end
$var wire 4 ! fault_code [3:0] $end
$var wire 1 " fault $end
$var reg 1 # ch1 $end
$var reg 1 $ ch2 $end
$var reg 1 % ch3 $end
$var reg 1 & ch4 $end
$var reg 1 ' clk $end
$var reg 1 ( rst $end
$scope module dut $end
$var wire 1 # ch1 $end
$var wire 1 $ ch2 $end
$var wire 1 % ch3 $end
$var wire 1 & ch4 $end
$var wire 1 ' clk $end
$var wire 1 ( rst $end
$var reg 1 " fault $end
$var reg 4 ) fault_code [3:0] $end
$upscope $end
$upscope $end
$enddefinitions $end
#0
$dumpvars
bx )
1(
0'
0&
0%
0$
0#
x"
bx !
$end
#5000
b0 !
b0 )
0"
1'
#10000
0'
0(
#15000
1'
#20000
0'
1#
#25000
b1000 !
b1000 )
1"
1'
#30000
0'
1$
0#
#35000
b100 !
b100 )
1'
#40000
0'
1%
0$
#45000
b10 !
b10 )
1'
#50000
0'
1&
0%
#55000
b1 !
b1 )
1'
#60000
0'
1%
1#
0&
#65000
b1000 !
b1000 )
1'
